jira_cli/__init__.py
jira_cli/main.py
jira_cli/model.py
jira_cli_top_moumoute-0.9.2.dist-info/METADATA
jira_cli_top_moumoute-0.9.2.dist-info/WHEEL
jira_cli_top_moumoute-0.9.2.dist-info/entry_points.txt
jira_cli_top_moumoute-0.9.2.dist-info/top_level.txt
jira_cli_top_moumoute-0.9.2.dist-info/RECORD
